huaweicloudsdktms/__init__.py
huaweicloudsdktms/v1/__init__.py
huaweicloudsdktms/v1/tms_async_client.py
huaweicloudsdktms/v1/tms_client.py
huaweicloudsdktms/v1/model/__init__.py
huaweicloudsdktms/v1/model/create_predefine_tags_request.py
huaweicloudsdktms/v1/model/create_predefine_tags_response.py
huaweicloudsdktms/v1/model/create_resource_tag_request.py
huaweicloudsdktms/v1/model/create_resource_tag_response.py
huaweicloudsdktms/v1/model/create_tag_request.py
huaweicloudsdktms/v1/model/delete_predefine_tags_request.py
huaweicloudsdktms/v1/model/delete_predefine_tags_response.py
huaweicloudsdktms/v1/model/delete_resource_tag_request.py
huaweicloudsdktms/v1/model/delete_resource_tag_response.py
huaweicloudsdktms/v1/model/delete_tag_request.py
huaweicloudsdktms/v1/model/errors.py
huaweicloudsdktms/v1/model/link.py
huaweicloudsdktms/v1/model/list_api_versions_request.py
huaweicloudsdktms/v1/model/list_api_versions_response.py
huaweicloudsdktms/v1/model/list_predefine_tags_request.py
huaweicloudsdktms/v1/model/list_predefine_tags_response.py
huaweicloudsdktms/v1/model/list_providers_request.py
huaweicloudsdktms/v1/model/list_providers_response.py
huaweicloudsdktms/v1/model/list_resource_request.py
huaweicloudsdktms/v1/model/list_resource_response.py
huaweicloudsdktms/v1/model/list_tag_keys_request.py
huaweicloudsdktms/v1/model/list_tag_keys_response.py
huaweicloudsdktms/v1/model/list_tag_values_request.py
huaweicloudsdktms/v1/model/list_tag_values_response.py
huaweicloudsdktms/v1/model/list_tags_request.py
huaweicloudsdktms/v1/model/list_tags_response.py
huaweicloudsdktms/v1/model/modify_prefine_tag.py
huaweicloudsdktms/v1/model/page_info_tag_keys.py
huaweicloudsdktms/v1/model/page_info_tag_values.py
huaweicloudsdktms/v1/model/predefine_tag.py
huaweicloudsdktms/v1/model/predefine_tag_request.py
huaweicloudsdktms/v1/model/provider_response_body.py
huaweicloudsdktms/v1/model/req_create_predefine_tag.py
huaweicloudsdktms/v1/model/req_create_tag.py
huaweicloudsdktms-3.1.184.dist-info/METADATA
huaweicloudsdktms-3.1.184.dist-info/WHEEL
huaweicloudsdktms-3.1.184.dist-info/licenses/LICENSE
huaweicloudsdktms-3.1.184.dist-info/RECORD
